pytrics/__init__.py
pytrics/tools.py
pytrics/common/__init__.py
pytrics/common/constants.py
pytrics/common/exceptions.py
pytrics/operations/__init__.py
pytrics/operations/download.py
pytrics/operations/upload.py
pytrics/qualtrics_api/__init__.py
pytrics/qualtrics_api/client.py
pytrics/qualtrics_api/common.py
pytrics/survey_definition/__init__.py
pytrics/survey_definition/agriculture/ET_en.py
pytrics/survey_definition/agriculture/IN_en.py
pytrics/survey_definition/agriculture/KE_en.py
pytrics/survey_definition/agriculture/NG_en.py
pytrics/survey_definition/agriculture/TZ_en.py
pytrics/survey_definition/agriculture/__init__.py
tests/__init__.py
tests/pytrics_helper_tests.py
tests/operations/__init__.py
tests/operations/download/__init__.py
tests/operations/download/await_response_file_creation_tests.py
tests/operations/download/get_file_path_tests.py
tests/operations/download/get_survey_and_response_data_tests.py
tests/operations/download/get_survey_data_tests.py
tests/operations/download/save_responses_to_s3_tests.py
tests/operations/download/save_survey_to_s3_tests.py
tests/operations/download/unzip_response_file_tests.py
tests/operations/upload/__init__.py
tests/operations/upload/create_survey_tests.py
tests/operations/upload/publish_survey_tests.py
tests/operations/upload/reference_data.py
tests/qualtrics_api/__init__.py
tests/qualtrics_api/client/__init__.py
tests/qualtrics_api/client/build_headers_tests.py
tests/qualtrics_api/client/initialisation_tests.py
tests/qualtrics_api/client/block/__init__.py
tests/qualtrics_api/client/block/create_block_tests.py
tests/qualtrics_api/client/block/get_block_tests.py
tests/qualtrics_api/client/block/update_block_tests.py
tests/qualtrics_api/client/block/validate_block_id_tests.py
tests/qualtrics_api/client/question/__init__.py
tests/qualtrics_api/client/question/build_question_display_logic_tests.py
tests/qualtrics_api/client/question/build_question_payload_tests.py
pytrics-1.1.0.dist-info/LICENSE.txt
pytrics-1.1.0.dist-info/METADATA
pytrics-1.1.0.dist-info/WHEEL
pytrics-1.1.0.dist-info/top_level.txt
pytrics-1.1.0.dist-info/RECORD
