Metadata-Version: 2.1
Name: pytrics
Version: 1.1.0
Summary: Python based Qualtrics survey integration
Home-page: https://github.com/60decibels/pytrics
Author: 60 Decibels Inc.
Author-email: tech@60decibels.com
License: GPLv2
Download-URL: https://pypi.org/project/pytrics/
Keywords: Qualtrics,Survey,Tool
Platform: UNKNOWN
Classifier: Programming Language :: Python :: 3.7
Classifier: Topic :: Scientific/Engineering :: Information Analysis
Classifier: Topic :: Software Development :: Libraries
Classifier: Intended Audience :: Developers
Classifier: Intended Audience :: Science/Research
Classifier: Development Status :: 4 - Beta
Classifier: License :: OSI Approved :: GNU General Public License v2 (GPLv2)
Requires-Dist: requests (>=2.21.0)
Requires-Dist: progress (>=1.5)
